ml_pipeline/ML_Feature.py
ml_pipeline/ML_Features.py
ml_pipeline/ML_Input_File.py
ml_pipeline/ML_Input_Files.py
ml_pipeline/ML_Model.py
ml_pipeline/ML_Models.py
ml_pipeline/ML_ParentClass.py
ml_pipeline/ML_params.py
ml_pipeline/ML_support.py
ml_pipeline/__init__.py
ml_pipeline/__main__.py
ml_pipeline/Templates/Input_File Child Class.py
ml_pipeline/Templates/__init__.py
ml_pipeline/Templates/main.ipynb
ml_pipeline/Templates/main.py
ml_pipeline/Templates/model_inputs.xlsx
ml_pipeline/Templates/code_templates/__init__.py
ml_pipeline/Templates/code_templates/algorithm.py
ml_pipeline/Templates/code_templates/generic_cleaning.py
ml_pipeline/Templates/code_templates/joining.py
ml_pipeline/Templates/code_templates/postprocessing.py
ml_pipeline/Templates/code_templates/preprocessing.py
ml_pipeline/Templates/main_class_templates/Feature.py
ml_pipeline/Templates/main_class_templates/Features.py
ml_pipeline/Templates/main_class_templates/Input_File.py
ml_pipeline/Templates/main_class_templates/Input_Files.py
ml_pipeline/Templates/main_class_templates/Model.py
ml_pipeline/Templates/main_class_templates/Models.py
ml_pipeline/Templates/main_class_templates/__init__.py
kabbes_ml_pipeline-0.6.0.dist-info/LICENSE
kabbes_ml_pipeline-0.6.0.dist-info/METADATA
kabbes_ml_pipeline-0.6.0.dist-info/WHEEL
kabbes_ml_pipeline-0.6.0.dist-info/top_level.txt
kabbes_ml_pipeline-0.6.0.dist-info/RECORD
