Metadata-Version: 2.1
Name: kabbes-ml-pipeline
Version: 0.6.0
Summary: A centralized pattern for creating Machine Learning pipelines
Home-page: https://pypi.org/project/kabbes_ml_pipeline
Author: James Kabbes
Author-email: james.kabbes@gmail.com
Project-URL: GitHub, https://github.com/jameskabbes/ml_pipeline
Project-URL: Documentation, https://jameskabbes.github.io/ml_pipeline
Classifier: Programming Language :: Python :: 3
Classifier: License :: OSI Approved :: MIT License
Classifier: Operating System :: OS Independent
Requires-Python: >=3.7
License-File: LICENSE
Requires-Dist: kabbes-py-starter
Requires-Dist: kabbes-parent-class
Requires-Dist: kabbes-analytics-packages
Requires-Dist: kabbes-dir-ops
Requires-Dist: kabbes-database-connections
Requires-Dist: pandas
Requires-Dist: numpy
Requires-Dist: matplotlib
Requires-Dist: shap
Requires-Dist: scikit-learn
